spacevlbi/Attitude.py
spacevlbi/Constraints.py
spacevlbi/Figures.py
spacevlbi/Observation.py
spacevlbi/Optimisation.py
spacevlbi/Orbit.py
spacevlbi/Station.py
spacevlbi/TimeLoop.py
spacevlbi/__init__.py
spacevlbi-1.1.10.dist-info/METADATA
spacevlbi-1.1.10.dist-info/WHEEL
spacevlbi-1.1.10.dist-info/licenses/LICENSE
spacevlbi-1.1.10.dist-info/RECORD
