Metadata-Version: 2.4
Name: spacevlbi
Version: 1.1.10
Summary: Python package to simulate and optimise space-based VLBI missions
Project-URL: Homepage, https://github.com/bhudson2/spacevlbi
Author-email: Ben Hudson <benhudson@tudelft.nl>
License: GNU GENERAL PUBLIC LICENSE
License-File: LICENSE
Keywords: Astronomy, VLBI, Space Mission Simulation, Mission Optimisation
Classifier: Development Status :: 4 - Beta
Classifier: License :: OSI Approved :: GNU General Public License v3 (GPLv3)
Classifier: Operating System :: OS Independent
Classifier: Programming Language :: Python :: 3.8
Requires-Python: >=3.8
Requires-Dist: astropy>=5.3.4
Requires-Dist: geopandas>=1.0.1
Requires-Dist: matplotlib>=3.9.1
Requires-Dist: numpy>=1.26.4
